cognition/__init__.py
cognition/api.py
cognition/crew.py
cognition/main.py
cognition/config/agents.yaml
cognition/config/crew.yaml
cognition/config/memory.yaml
cognition/config/portkey.yaml
cognition/config/tasks.yaml
cognition/config/tools.yaml
cognition/config/tools/tool_001.py
"cognition/config/tools/core/__init__,py"
cognition/tools/__init__.py
cognition/tools/custom_tool.py
cognition_ai-0.3.0.dist-info/METADATA
cognition_ai-0.3.0.dist-info/WHEEL
cognition_ai-0.3.0.dist-info/entry_points.txt
cognition_ai-0.3.0.dist-info/RECORD
